empyric/__init__.py
empyric/__main__.py
empyric/adapters.py
empyric/collection/__init__.py
empyric/collection/barometers.py
empyric/collection/controllers.py
empyric/collection/generators.py
empyric/collection/humans.py
empyric/collection/instrument.py
empyric/collection/io.py
empyric/collection/magnetometers.py
empyric/collection/multimeters.py
empyric/collection/scopes.py
empyric/collection/sourcemeters.py
empyric/collection/spectrometers.py
empyric/collection/supplies.py
empyric/collection/thermometers.py
empyric/collection/virtual.py
empyric/experiment.py
empyric/graphics.py
empyric/instruments.py
empyric/routines.py
empyric/runcard_schema.yaml
empyric/tests/__init__.py
empyric/tests/henon_runcard_example.yaml
empyric/tests/test_adapter.py
empyric/tests/test_experiment.py
empyric/tests/test_variable.py
empyric/tools.py
empyric/types.py
empyric/variables.py
empyric-0.3.1.dist-info/entry_points.txt
empyric-0.3.1.dist-info/LICENSE
empyric-0.3.1.dist-info/METADATA
empyric-0.3.1.dist-info/WHEEL
empyric-0.3.1.dist-info/RECORD
