Metadata-Version: 2.3
Name: empyric
Version: 0.3.1
Summary: A package for experiment automation
Author: Daniel Merthe
Author-email: dmerthe@gmail.com
Requires-Python: >=3.11,<4.0
Classifier: License :: OSI Approved :: MIT License
Classifier: Operating System :: OS Independent
Classifier: Programming Language :: Python :: 3
Classifier: Programming Language :: Python :: 3.11
Classifier: Programming Language :: Python :: 3.12
Classifier: Programming Language :: Python :: 3.13
Requires-Dist: bayesian-optimization (==1.4.3)
Requires-Dist: dill (==0.3.7)
Requires-Dist: matplotlib (==3.9.2)
Requires-Dist: numpy (==2.1.3)
Requires-Dist: pandas (==2.2.3)
Requires-Dist: pykwalify (==1.8.0)
Requires-Dist: pytest (==8.3.3)
Requires-Dist: ruamel.yaml (==0.17.21)
Requires-Dist: scipy (==1.14.1)
Project-URL: Repository, https://github.com/dmerthe/empyric
